LICENSE.txt
MANIFEST.in
README.rst
setup.py
umansysprop/__init__.py
umansysprop/client.py
umansysprop/forms.py
umansysprop/html.py
umansysprop/renderers.py
umansysprop/results.py
umansysprop/server.py
umansysprop/zip.py
umansysprop.egg-info/PKG-INFO
umansysprop.egg-info/SOURCES.txt
umansysprop.egg-info/dependency_links.txt
umansysprop.egg-info/entry_points.txt
umansysprop.egg-info/requires.txt
umansysprop.egg-info/top_level.txt
umansysprop/tools/__init__.py
umansysprop/tools/test.py