Metadata-Version: 1.1
Name: umansysprop
Version: 0.1
Summary: An online system for calculating the properties of individual organic
Home-page: http://umansysprop.readthedocs.org/
Author: Dave Hughes
Author-email: dave@waveform.org.uk
License: GNU General Public License v2 or later (GPLv2+)
Keywords: science,organic,chemistry
Platform: A
Platform: L
Platform: L
Classifier: Development Status :: 4 - Beta
Classifier: Environment :: Web Environment
Classifier: Intended Audience :: Science/Research
Classifier: License :: OSI Approved :: GNU General Public License v2 or later (GPLv2+)
Classifier: Operating System :: POSIX
Classifier: Operating System :: Unix
Classifier: Programming Language :: Python :: 2.7
Classifier: Programming Language :: Python :: 3
Classifier: Topic :: Scientific/Engineering :: Atmospheric Science
